mxsearchstorage/__init__.py
mxsearchstorage/blob.py
mxsearchstorage/schema.py
mxsearchstorage-1.0.5.dist-info/METADATA
mxsearchstorage-1.0.5.dist-info/WHEEL
mxsearchstorage-1.0.5.dist-info/top_level.txt
mxsearchstorage-1.0.5.dist-info/RECORD
