Metadata-Version: 2.1
Name: mxsearchstorage
Version: 1.0.5
Summary: Mexico search object store Library
Home-page: UNKNOWN
Author: blake
Author-email: huiblake.li@walmart.com
License: UNKNOWN
Platform: UNKNOWN
Requires-Dist: azure-core
Requires-Dist: azure-storage-blob
Requires-Dist: certifi
Requires-Dist: charset-normalizer
Requires-Dist: cryptography
Requires-Dist: idna
Requires-Dist: isodate
Requires-Dist: msrest
Requires-Dist: oauthlib
Requires-Dist: pycparser
Requires-Dist: requests
Requires-Dist: requests-oauthlib
Requires-Dist: six
Requires-Dist: urllib3
